{"ITEMID": "001-155654", "LANGUAGEISOCODE": "ENG", "RESPONDENT": "ESP", "BRANCH": "ADMISSIBILITY", "DATE": 2015, "DOCNAME": "SOBERAN\u00cdA DE LA RAZ\u00d3N AND OTHERS v. SPAIN", "IMPORTANCE": "4", "CONCLUSION": "Inadmissible", "JUDGES": "Branko Lubarda;J\u00e1n \u0160ikuta;Johannes Silvis;Josep Casadevall;Luis L\u00f3pez Guerra", "TEXT": ["CARDINAL . The first applicant , PERSON , is a NORP political party registered with ORG in DATE . The second and the third applicants , Ms. PERSON and Mr. PERSON Luis Maz\u00f3n Costa , are NORP nationals who stood as CARDINAL of the first applicant \u2019s candidates for the DATE elections to ORG . The applicants are represented before the ORG by the third applicant , Mr. PERSON Costa , a lawyer in GPE . A list of the applicants is set out in the appendix ."], "VIOLATED_ARTICLES": [], "VIOLATED_PARAGRAPHS": [], "VIOLATED_BULLETPOINTS": [], "NON_VIOLATED_ARTICLES": [], "NON_VIOLATED_PARAGRAPHS": [], "NON_VIOLATED_BULLETPOINTS": []}