{"ITEMID": "001-22886", "LANGUAGEISOCODE": "ENG", "RESPONDENT": "UKR", "BRANCH": "ADMISSIBILITY", "DATE": 2002, "DOCNAME": "SOKUR v. Ukraine", "IMPORTANCE": "3", "CONCLUSION": "Inadmissible", "JUDGES": "Gaukur J\u00f6rundsson", "TEXT": ["The applicant , PERSON , is a NORP national , who was born in DATE and resides in the village of GPE , GPE , GPE .", "The facts of the case , as submitted by the applicant , may be summarised as follows .", "In DATE , the applicant instituted proceedings in ORG of GPE against the \u201c ORG - a ORG - owned enterprise - to recover unpaid salary for DATE .", "On DATE , ORG found in favour of the applicant ( ORG \u0433\u043e\u0440\u043e\u0434\u0441\u043a\u043e\u0433\u043e \u0441\u0443\u0434\u0430 PERSON \u043e\u0431\u043b\u0430\u0441\u0442\u0438 ) . The decision became effective on DATE and was sent for execution to ORG ( \u041e\u0442\u0434\u0435\u043b \u0413\u043e\u0441\u0443\u0434\u0430\u0440\u0441\u0442\u0432\u0435\u043d\u043d\u043e\u0439 \u0438\u0441\u043f\u043e\u043b\u043d\u0438\u0442\u0435\u043b\u044c\u043d\u043e\u0439 \u0441\u043b\u0443\u0436\u0431\u044b \u041d\u043e\u0432\u043e\u0433\u0440\u043e\u0434\u043e\u0432\u0441\u043a\u043e\u0433\u043e \u0433\u043e\u0440\u043e\u0434\u0441\u043a\u043e\u0433\u043e \u0443\u043f\u0440\u0430\u0432\u043b\u0435\u043d\u0438\u044f \u044e\u0441\u0442\u0438\u0446\u0438\u0438 ) . However , the decision was not executed , allegedly due to the failure of ORG to act , in not selling the property of ORG .", "The applicant instituted proceedings in ORG of GPE against ORG for failure to execute the court decision in his favour . On DATE , ORG rejected the applicant \u2019s claim , finding no fault had been committed by ORG . The court stated that ORG had presented the decision of ORG of GPE of DATE to the respondent company , but was prohibited from enforcing the decision by selling the property of the mine , due to the bankruptcy proceedings which had been initiated against it .", "On DATE , ORG dismissed the applicant \u2019s appeal . On DATE , the panel of CARDINAL judges of ORG of ORG of GPE rejected the applicant \u2019s request for leave to appeal .", "On DATE , the ban on the forced sale of assets belonging to undertakings in which the ORG holds PERCENT of the share capital , was entrenched in the PERSON on the Introduction of a Moratorium on the Forced Sale of Property .", "Under LAW of the LAW on bankruptcy ( ORG \u0432\u0456\u0434\u043d\u043e\u0432\u043b\u0435\u043d\u043d\u044f \u043f\u043b\u0430\u0442\u043e\u0441\u043f\u0440\u043e\u043c\u043e\u0436\u043d\u043e\u0441\u0442\u0456 \u0431\u043e\u0440\u0436\u043d\u0438\u043a\u0430 \u0430\u0431\u043e \u0432\u0438\u0437\u043d\u0430\u043d\u043d\u044f \u0439\u043e\u0433\u043e \u0431\u0430\u043d\u043a\u0440\u0443\u0442\u043e\u043c ORG ) , a commercial court is entitled to order a moratorium on debt recovery from a company subject to bankruptcy proceedings . The moratorium implies a prohibition on ORG to execute judgements against such a company .", "The PERSON on the Introduction of a Moratorium on the Forced Sale of Property ( ORG \u041f\u0440\u043e \u0432\u0432\u0435\u0434\u0435\u043d\u043d\u044f \u043c\u043e\u0440\u0430\u0442\u043e\u0440i\u044e \u043d\u0430 \u043f\u0440\u0438\u043c\u0443\u0441\u043e\u0432\u0443 \u0440\u0435\u0430\u043bi\u0437\u0430\u0446i\u044e TIME \u201d ) aims at protecting ORG interests on the sale of assets belonging to undertakings in which the ORG holds PERCENT of the share capital .", "A moratorium on the enforcement of judgment debts has been introduced until such time as the mechanism for the forced sale of the property of such undertakings has been improved . No time - limit has been set .", "Section CARDINAL of that PERSON provides that the prohibition on the forced sale of property includes the execution of writs by ORG over property belonging to such companies .", "The PERSON therefore stays the execution of all writs by ORG against the assets of undertakings in which the ORG holds PERCENT of the share capital ."], "VIOLATED_ARTICLES": [], "VIOLATED_PARAGRAPHS": [], "VIOLATED_BULLETPOINTS": [], "NON_VIOLATED_ARTICLES": [], "NON_VIOLATED_PARAGRAPHS": [], "NON_VIOLATED_BULLETPOINTS": []}